kinto_changes/__init__.py
kinto_changes/utils.py
kinto_changes/views.py
kinto_changes-4.1.2.dist-info/LICENSE
kinto_changes-4.1.2.dist-info/METADATA
kinto_changes-4.1.2.dist-info/WHEEL
kinto_changes-4.1.2.dist-info/top_level.txt
kinto_changes-4.1.2.dist-info/RECORD
