Metadata-Version: 2.1
Name: kinto-changes
Version: 4.1.2
Summary: Plug Kinto notifications to a collection endpoint.
Home-page: https://github.com/kinto/kinto-changes
Author: Mozilla Services
Author-email: services-dev@mozilla.com
License: Apache License (2.0)
Keywords: kinto changes notification
Platform: UNKNOWN
Classifier: Development Status :: 7 - Inactive
Classifier: Intended Audience :: Developers
Classifier: License :: OSI Approved :: Apache Software License
Classifier: Natural Language :: English
Classifier: Programming Language :: Python :: 3
Classifier: Programming Language :: Python :: 3.5
Classifier: Programming Language :: Python :: 3.6
Requires-Dist: kinto (>=10.0.0)
